test_appz/__init__.py
test_appz/__main__.py
test_appz-0.1.1.dist-info/METADATA
test_appz-0.1.1.dist-info/WHEEL
test_appz-0.1.1.dist-info/top_level.txt
test_appz-0.1.1.dist-info/RECORD
